qai/storage/__init__.py
qai/storage/aws/aws.py
qai/storage/aws/aws_history.py
qai/storage/history/__init__.py
qai/storage/history/history_maker.py
qai/storage/history.py
qai/storage/llama/llama_adapter.py
qai/storage/llama/openai_llm.py
qai/storage/llama/wrapper.py
qai/storage/retriever.py
qai_storage-0.6.1.dist-info/METADATA
qai_storage-0.6.1.dist-info/WHEEL
qai_storage-0.6.1.dist-info/RECORD
